diffutils/__init__.py
diffutils/__main__.py
diffutils/_myers.py
diffutils/api.py
diffutils/core.py
diffutils/engine.py
diffutils/output.py
diffutils/_native/__init__.py
diffutils/_native/myers.cpython-39-darwin.so
diffutils-1.0.7.dist-info/LICENCE
diffutils-1.0.7.dist-info/METADATA
diffutils-1.0.7.dist-info/WHEEL
diffutils-1.0.7.dist-info/top_level.txt
diffutils-1.0.7.dist-info/RECORD
