Metadata-Version: 2.1
Name: diffutils
Version: 1.0.7
Summary: A python diff/patch library, with support for unified diffs and a native diff implementation
Author: Techcable
Author-email: Techcable@outlook.com
License: MIT
Keywords: diff patch myers
Platform: UNKNOWN
Classifier: License :: OSI Approved :: MIT License
Classifier: Programming Language :: Python :: 3.5
Classifier: Programming Language :: Python :: 3.6
Requires: argh
License-File: LICENCE
